[
    {
        "FilterDataType": "ID",
        "FilterGroup": 0,
        "FilterOperator": "=",
        "FilterValue": "obj:recId",
        "GlobalKey": "DR_TurboExtract_GetContactDetails4083912252187787",
        "InputFieldName": "Id",
        "InputObjectName": "Contact",
        "InputObjectQuerySequence": 1,
        "IsDisabled": false,
        "IsRequiredForUpsert": false,
        "IsUpsertKey": false,
        "Name": "DR_TurboExtract_GetContactDetails",
        "OmniDataTransformationId": {
            "Name": "DR_TurboExtract_GetContactDetails",
            "VlocityDataPackType": "VlocityMatchingKeyObject",
            "VlocityMatchingRecordSourceKey": "OmniDataTransform/DR_TurboExtract_GetContactDetails",
            "VlocityRecordSObjectType": "OmniDataTransform"
        },
        "OutputCreationSequence": 0,
        "OutputFieldName": "contacts",
        "OutputObjectName": "Turbo Extract",
        "VlocityDataPackType": "SObject",
        "VlocityRecordSObjectType": "OmniDataTransformItem"
    },
    {
        "GlobalKey": "DR_TurboExtract_GetContactDetails995129345821254",
        "InputFieldName": "Account.Name",
        "InputObjectName": "Contact",
        "IsDisabled": false,
        "IsRequiredForUpsert": false,
        "IsUpsertKey": false,
        "Name": "DR_TurboExtract_GetContactDetails",
        "OmniDataTransformationId": {
            "Name": "DR_TurboExtract_GetContactDetails",
            "VlocityDataPackType": "VlocityMatchingKeyObject",
            "VlocityMatchingRecordSourceKey": "OmniDataTransform/DR_TurboExtract_GetContactDetails",
            "VlocityRecordSObjectType": "OmniDataTransform"
        },
        "OutputCreationSequence": 1,
        "OutputFieldName": "contacts",
        "OutputObjectName": "Turbo Extract",
        "VlocityDataPackType": "SObject",
        "VlocityRecordSObjectType": "OmniDataTransformItem"
    },
    {
        "GlobalKey": "DR_TurboExtract_GetContactDetails7448862537302852",
        "InputFieldName": "FirstName",
        "InputObjectName": "Contact",
        "IsDisabled": false,
        "IsRequiredForUpsert": false,
        "IsUpsertKey": false,
        "Name": "DR_TurboExtract_GetContactDetails",
        "OmniDataTransformationId": {
            "Name": "DR_TurboExtract_GetContactDetails",
            "VlocityDataPackType": "VlocityMatchingKeyObject",
            "VlocityMatchingRecordSourceKey": "OmniDataTransform/DR_TurboExtract_GetContactDetails",
            "VlocityRecordSObjectType": "OmniDataTransform"
        },
        "OutputCreationSequence": 1,
        "OutputFieldName": "contacts",
        "OutputObjectName": "Turbo Extract",
        "VlocityDataPackType": "SObject",
        "VlocityRecordSObjectType": "OmniDataTransformItem"
    },
    {
        "GlobalKey": "DR_TurboExtract_GetContactDetails5388386397344722",
        "InputFieldName": "LastName",
        "InputObjectName": "Contact",
        "IsDisabled": false,
        "IsRequiredForUpsert": false,
        "IsUpsertKey": false,
        "Name": "DR_TurboExtract_GetContactDetails",
        "OmniDataTransformationId": {
            "Name": "DR_TurboExtract_GetContactDetails",
            "VlocityDataPackType": "VlocityMatchingKeyObject",
            "VlocityMatchingRecordSourceKey": "OmniDataTransform/DR_TurboExtract_GetContactDetails",
            "VlocityRecordSObjectType": "OmniDataTransform"
        },
        "OutputCreationSequence": 1,
        "OutputFieldName": "contacts",
        "OutputObjectName": "Turbo Extract",
        "VlocityDataPackType": "SObject",
        "VlocityRecordSObjectType": "OmniDataTransformItem"
    }
]