{
    "IsActive": true,
    "IsOmniScriptEmbeddable": false,
    "Name": "Multi-select1",
    "OmniProcessId": {
        "Name": "OS_InputElements_SelectMultiRadio",
        "VlocityDataPackType": "VlocityMatchingKeyObject",
        "VlocityMatchingRecordSourceKey": "OmniProcess/OS_InputElements_SelectMultiRadio/OS_InputElements_SelectMultiRadio/English",
        "VlocityRecordSObjectType": "OmniProcess"
    },
    "ParentElementId": {
        "Name": "Step1",
        "OmniProcessId": {
            "Name": "OS_InputElements_SelectMultiRadio",
            "VlocityDataPackType": "VlocityMatchingKeyObject",
            "VlocityMatchingRecordSourceKey": "OmniProcess/OS_InputElements_SelectMultiRadio/OS_InputElements_SelectMultiRadio/English",
            "VlocityRecordSObjectType": "OmniProcess"
        },
        "VlocityDataPackType": "VlocityMatchingKeyObject",
        "VlocityMatchingRecordSourceKey": "OmniProcessElement/OmniProcess/OS_InputElements_SelectMultiRadio/OS_InputElements_SelectMultiRadio/English/Step1",
        "VlocityRecordSObjectType": "OmniProcessElement"
    },
    "ParentElementName": "Step1",
    "ParentElementType": "Step",
    "PropertySetConfig": {
        "HTMLTemplateId": "",
        "accessibleInFutureSteps": false,
        "conditionType": "Hide if False",
        "controlWidth": 12,
        "controllingField": {
            "element": "",
            "source": "",
            "type": ""
        },
        "defaultValue": null,
        "disOnTplt": false,
        "enableCaption": true,
        "help": false,
        "helpText": "",
        "helpTextPos": "",
        "hide": false,
        "horizontalMode": false,
        "imageCountInRow": 3,
        "label": "Multi-select1",
        "optionHeight": 100,
        "optionSource": {
            "source": "Case.Status",
            "type": "SObject"
        },
        "optionWidth": 100,
        "options": [
        ],
        "readOnly": false,
        "repeat": false,
        "repeatClone": false,
        "repeatLimit": null,
        "required": false,
        "show": null
    },
    "Type": "Multi-select",
    "VlocityDataPackType": "SObject",
    "VlocityRecordSObjectType": "OmniProcessElement",
    "VlocityRecordSourceKey": "OmniProcessElement/OmniProcess/OS_InputElements_SelectMultiRadio/OS_InputElements_SelectMultiRadio/English/Multi-select1"
}